[
    {
        "coord": {
            "lon": 9.9187,
            "lat": 57.048
        },
        "weather": [
            {
                "id": 800,
                "main": "Clear",
                "description": "cielo claro",
                "icon": "01n"
            }
        ],
        "base": "stations",
        "main": {
            "temp": 17.96,
            "feels_like": 17.82,
            "temp_min": 17.96,
            "temp_max": 17.96,
            "pressure": 1024,
            "humidity": 77,
            "sea_level": 1024,
            "grnd_level": 1022
        },
        "visibility": 10000,
        "wind": {
            "speed": 4.12,
            "deg": 80
        },
        "clouds": {
            "all": 0
        },
        "dt": 1725574187,
        "sys": {
            "type": 1,
            "id": 1600,
            "country": "DK",
            "sunrise": 1725597203,
            "sunset": 1725645853
        },
        "timezone": 7200,
        "id": 2624886,
        "name": "Aalborg",
        "cod": 200
    },
    {
        "coord": {
            "lon": 10.2108,
            "lat": 56.1567
        },
        "weather": [
            {
                "id": 802,
                "main": "Clouds",
                "description": "nubes dispersas",
                "icon": "03n"
            }
        ],
        "base": "stations",
        "main": {
            "temp": 19.9,
            "feels_like": 19.93,
            "temp_min": 19.77,
            "temp_max": 21.12,
            "pressure": 1023,
            "humidity": 76,
            "sea_level": 1023,
            "grnd_level": 1018
        },
        "visibility": 10000,
        "wind": {
            "speed": 6.72,
            "deg": 85,
            "gust": 15.09
        },
        "clouds": {
            "all": 41
        },
        "dt": 1725574075,
        "sys": {
            "type": 2,
            "id": 2001568,
            "country": "DK",
            "sunrise": 1725597221,
            "sunset": 1725645694
        },
        "timezone": 7200,
        "id": 2624652,
        "name": "Aarhus",
        "cod": 200
    },
    {
        "coord": {
            "lon": 48.3043,
            "lat": 30.3392
        },
        "weather": [
            {
                "id": 800,
                "main": "Clear",
                "description": "cielo claro",
                "icon": "01n"
            }
        ],
        "base": "stations",
        "main": {
            "temp": 34.25,
            "feels_like": 31.75,
            "temp_min": 34.25,
            "temp_max": 34.25,
            "pressure": 1000,
            "humidity": 13,
            "sea_level": 1000,
            "grnd_level": 1000
        },
        "visibility": 10000,
        "wind": {
            "speed": 5.34,
            "deg": 309,
            "gust": 8.91
        },
        "clouds": {
            "all": 0
        },
        "dt": 1725574190,
        "sys": {
            "country": "IR",
            "sunrise": 1725589591,
            "sunset": 1725635044
        },
        "timezone": 12600,
        "id": 145459,
        "name": "\u0100b\u0101d\u0101n",
        "cod": 200
    },
    {
        "coord": {
            "lon": 91.4292,
            "lat": 53.7156
        },
        "weather": [
            {
                "id": 800,
                "main": "Clear",
                "description": "cielo claro",
                "icon": "01n"
            }
        ],
        "base": "stations",
        "main": {
            "temp": 13.01,
            "feels_like": 12.82,
            "temp_min": 13.01,
            "temp_max": 13.01,
            "pressure": 1008,
            "humidity": 94,
            "sea_level": 1008,
            "grnd_level": 978
        },
        "visibility": 10000,
        "wind": {
            "speed": 2,
            "deg": 350
        },
        "clouds": {
            "all": 0
        },
        "dt": 1725574192,
        "sys": {
            "type": 1,
            "id": 8942,
            "country": "RU",
            "sunrise": 1725577926,
            "sunset": 1725626014
        },
        "timezone": 25200,
        "id": 1512236,
        "name": "Abakan",
        "cod": 200
    },
    {
        "coord": {
            "lon": -2.0981,
            "lat": 57.1437
        },
        "weather": [
            {
                "id": 701,
                "main": "Mist",
                "description": "niebla",
                "icon": "50n"
            }
        ],
        "base": "stations",
        "main": {
            "temp": 13.12,
            "feels_like": 13.1,
            "temp_min": 12.89,
            "temp_max": 13.27,
            "pressure": 1024,
            "humidity": 100,
            "sea_level": 1024,
            "grnd_level": 1019
        },
        "visibility": 4100,
        "wind": {
            "speed": 5.14,
            "deg": 330
        },
        "clouds": {
            "all": 100
        },
        "dt": 1725574193,
        "sys": {
            "type": 1,
            "id": 1440,
            "country": "GB",
            "sunrise": 1725513559,
            "sunset": 1725562505
        },
        "timezone": 3600,
        "id": 2657832,
        "name": "Aberdeen",
        "cod": 200
    },
    {
        "coord": {
            "lon": 42.5053,
            "lat": 18.2164
        },
        "weather": [
            {
                "id": 800,
                "main": "Clear",
                "description": "cielo claro",
                "icon": "01n"
            }
        ],
        "base": "stations",
        "main": {
            "temp": 18.14,
            "feels_like": 17.79,
            "temp_min": 18.14,
            "temp_max": 18.14,
            "pressure": 1011,
            "humidity": 68,
            "sea_level": 1011,
            "grnd_level": 809
        },
        "visibility": 10000,
        "wind": {
            "speed": 0,
            "deg": 0
        },
        "clouds": {
            "all": 0
        },
        "dt": 1725574196,
        "sys": {
            "type": 1,
            "id": 7396,
            "country": "SA",
            "sunrise": 1725591396,
            "sunset": 1725636022
        },
        "timezone": 10800,
        "id": 110690,
        "name": "Abh\u0101",
        "cod": 200
    },
    {
        "coord": {
            "lon": 54.3667,
            "lat": 24.4667
        },
        "weather": [
            {
                "id": 801,
                "main": "Clouds",
                "description": "algo de nubes",
                "icon": "02n"
            }
        ],
        "base": "stations",
        "main": {
            "temp": 33.86,
            "feels_like": 40.86,
            "temp_min": 33.86,
            "temp_max": 33.86,
            "pressure": 1000,
            "humidity": 74,
            "sea_level": 1000,
            "grnd_level": 1000
        },
        "visibility": 10000,
        "wind": {
            "speed": 1.66,
            "deg": 63,
            "gust": 1.52
        },
        "clouds": {
            "all": 13
        },
        "dt": 1725574197,
        "sys": {
            "type": 2,
            "id": 2032466,
            "country": "AE",
            "sunrise": 1725588347,
            "sunset": 1725633379
        },
        "timezone": 14400,
        "id": 292968,
        "name": "Abu Dhabi",
        "cod": 200
    },
    {
        "coord": {
            "lon": -4.0197,
            "lat": 5.3094
        },
        "weather": [
            {
                "id": 803,
                "main": "Clouds",
                "description": "muy nuboso",
                "icon": "04n"
            }
        ],
        "base": "stations",
        "main": {
            "temp": 24.98,
            "feels_like": 25.83,
            "temp_min": 24.98,
            "temp_max": 24.98,
            "pressure": 1015,
            "humidity": 88,
            "sea_level": 1015,
            "grnd_level": 1014
        },
        "visibility": 9000,
        "wind": {
            "speed": 2.06,
            "deg": 210
        },
        "clouds": {
            "all": 75
        },
        "dt": 1725574199,
        "sys": {
            "type": 1,
            "id": 1162,
            "country": "CI",
            "sunrise": 1725516542,
            "sunset": 1725560443
        },
        "timezone": 0,
        "id": 2293538,
        "name": "Abidjan",
        "cod": 200
    },
    {
        "coord": {
            "lon": -99.7331,
            "lat": 32.4487
        },
        "weather": [
            {
                "id": 804,
                "main": "Clouds",
                "description": "nubes",
                "icon": "04d"
            }
        ],
        "base": "stations",
        "main": {
            "temp": 28.21,
            "feels_like": 29.76,
            "temp_min": 27.19,
            "temp_max": 29.12,
            "pressure": 1017,
            "humidity": 60,
            "sea_level": 1017,
            "grnd_level": 954
        },
        "visibility": 10000,
        "wind": {
            "speed": 4.63,
            "deg": 20
        },
        "clouds": {
            "all": 100
        },
        "dt": 1725573944,
        "sys": {
            "type": 1,
            "id": 3206,
            "country": "US",
            "sunrise": 1725538615,
            "sunset": 1725584302
        },
        "timezone": -18000,
        "id": 4669635,
        "name": "Abilene",
        "cod": 200
    },
    {
        "coord": {
            "lon": 7.4898,
            "lat": 9.0574
        },
        "weather": [
            {
                "id": 501,
                "main": "Rain",
                "description": "lluvia moderada",
                "icon": "10n"
            }
        ],
        "base": "stations",
        "main": {
            "temp": 22.08,
            "feels_like": 22.82,
            "temp_min": 22.08,
            "temp_max": 22.08,
            "pressure": 1014,
            "humidity": 95,
            "sea_level": 1014,
            "grnd_level": 960
        },
        "visibility": 10000,
        "wind": {
            "speed": 1.42,
            "deg": 273,
            "gust": 2.68
        },
        "rain": {
            "1h": 1.23
        },
        "clouds": {
            "all": 100
        },
        "dt": 1725574201,
        "sys": {
            "country": "NG",
            "sunrise": 1725513672,
            "sunset": 1725557790
        },
        "timezone": 3600,
        "id": 2352778,
        "name": "Abuja",
        "cod": 200
    }
]